{
  "gainers": [
    {
      "time": "3:52:49 AM",
      "data": [
        {
          "company": "Hero Motocorp",
          "high": "5,564.95",
          "low": "5,499.85",
          "lastPrice": "5,553.20",
          "prevClose": "5,476.30",
          "change": "76.90",
          "percentGain": "1.40"
        },
        {
          "company": "Larsen",
          "high": "3,541.05",
          "low": "3,501.30",
          "lastPrice": "3,531.10",
          "prevClose": "3,482.55",
          "change": "48.55",
          "percentGain": "1.39"
        },
        {
          "company": "JSW Steel",
          "high": "1,032.00",
          "low": "1,015.00",
          "lastPrice": "1,025.10",
          "prevClose": "1,012.05",
          "change": "13.05",
          "percentGain": "1.29"
        },
        {
          "company": "Tech Mahindra",
          "high": "1,661.00",
          "low": "1,648.00",
          "lastPrice": "1,659.20",
          "prevClose": "1,647.05",
          "change": "12.15",
          "percentGain": "0.74"
        },
        {
          "company": "Shriram Finance",
          "high": "3,388.80",
          "low": "3,353.75",
          "lastPrice": "3,365.60",
          "prevClose": "3,341.20",
          "change": "24.40",
          "percentGain": "0.73"
        }
      ]
    },
    {
      "time": "4:18:51 AM",
      "data": []
    },
    {
      "time": "4:41:46 AM",
      "data": []
    },
    {
      "time": "4:51:34 AM",
      "data": [
        {
          "company": "Wipro",
          "high": "545.50",
          "low": "536.30",
          "lastPrice": "539.45",
          "prevClose": "528.30",
          "change": "11.15",
          "percentGain": "2.11"
        },
        {
          "company": "Larsen",
          "high": "3,556.90",
          "low": "3,501.30",
          "lastPrice": "3,544.30",
          "prevClose": "3,482.55",
          "change": "61.75",
          "percentGain": "1.77"
        },
        {
          "company": "Coal India",
          "high": "502.45",
          "low": "492.95",
          "lastPrice": "501.65",
          "prevClose": "492.95",
          "change": "8.70",
          "percentGain": "1.76"
        },
        {
          "company": "Shriram Finance",
          "high": "3,430.00",
          "low": "3,353.75",
          "lastPrice": "3,393.05",
          "prevClose": "3,341.20",
          "change": "51.85",
          "percentGain": "1.55"
        },
        {
          "company": "BPCL",
          "high": "344.60",
          "low": "339.40",
          "lastPrice": "342.65",
          "prevClose": "337.65",
          "change": "5.00",
          "percentGain": "1.48"
        }
      ]
    },
    {
      "time": "5:15:55 AM",
      "data": []
    },
    {
      "time": "5:39:38 AM",
      "data": [
        {
          "company": "Wipro",
          "high": "545.50",
          "low": "536.30",
          "lastPrice": "538.85",
          "prevClose": "528.30",
          "change": "10.55",
          "percentGain": "2.00"
        },
        {
          "company": "HDFC Bank",
          "high": "1,682.95",
          "low": "1,654.00",
          "lastPrice": "1,682.80",
          "prevClose": "1,651.00",
          "change": "31.80",
          "percentGain": "1.93"
        },
        {
          "company": "Larsen",
          "high": "3,556.90",
          "low": "3,501.30",
          "lastPrice": "3,543.05",
          "prevClose": "3,482.55",
          "change": "60.50",
          "percentGain": "1.74"
        },
        {
          "company": "Kotak Mahindra",
          "high": "1,912.50",
          "low": "1,882.45",
          "lastPrice": "1,912.50",
          "prevClose": "1,882.40",
          "change": "30.10",
          "percentGain": "1.60"
        },
        {
          "company": "Tech Mahindra",
          "high": "1,672.90",
          "low": "1,648.00",
          "lastPrice": "1,672.50",
          "prevClose": "1,647.05",
          "change": "25.45",
          "percentGain": "1.55"
        }
      ]
    },
    {
      "time": "5:49:58 AM",
      "data": [
        {
          "company": "HDFC Bank",
          "high": "1,685.00",
          "low": "1,654.00",
          "lastPrice": "1,683.45",
          "prevClose": "1,651.00",
          "change": "32.45",
          "percentGain": "1.97"
        },
        {
          "company": "Wipro",
          "high": "545.50",
          "low": "536.30",
          "lastPrice": "538.55",
          "prevClose": "528.30",
          "change": "10.25",
          "percentGain": "1.94"
        },
        {
          "company": "Larsen",
          "high": "3,556.90",
          "low": "3,501.30",
          "lastPrice": "3,548.55",
          "prevClose": "3,482.55",
          "change": "66.00",
          "percentGain": "1.90"
        },
        {
          "company": "Shriram Finance",
          "high": "3,430.00",
          "low": "3,353.75",
          "lastPrice": "3,402.05",
          "prevClose": "3,341.20",
          "change": "60.85",
          "percentGain": "1.82"
        },
        {
          "company": "Tech Mahindra",
          "high": "1,677.50",
          "low": "1,648.00",
          "lastPrice": "1,675.30",
          "prevClose": "1,647.05",
          "change": "28.25",
          "percentGain": "1.72"
        }
      ]
    },
    {
      "time": "6:22:58 AM",
      "data": [
        {
          "company": "Wipro",
          "high": "545.50",
          "low": "536.30",
          "lastPrice": "541.90",
          "prevClose": "528.30",
          "change": "13.60",
          "percentGain": "2.57"
        },
        {
          "company": "Tech Mahindra",
          "high": "1,685.80",
          "low": "1,648.00",
          "lastPrice": "1,685.15",
          "prevClose": "1,647.05",
          "change": "38.10",
          "percentGain": "2.31"
        },
        {
          "company": "HDFC Life",
          "high": "739.50",
          "low": "726.30",
          "lastPrice": "738.00",
          "prevClose": "723.85",
          "change": "14.15",
          "percentGain": "1.95"
        },
        {
          "company": "HDFC Bank",
          "high": "1,685.00",
          "low": "1,654.00",
          "lastPrice": "1,683.00",
          "prevClose": "1,651.00",
          "change": "32.00",
          "percentGain": "1.94"
        },
        {
          "company": "Larsen",
          "high": "3,556.90",
          "low": "3,501.30",
          "lastPrice": "3,550.00",
          "prevClose": "3,482.55",
          "change": "67.45",
          "percentGain": "1.94"
        }
      ]
    },
    {
      "time": "6:45:55 AM",
      "data": [
        {
          "company": "Wipro",
          "high": "545.50",
          "low": "536.30",
          "lastPrice": "542.70",
          "prevClose": "528.30",
          "change": "14.40",
          "percentGain": "2.73"
        },
        {
          "company": "Tech Mahindra",
          "high": "1,689.00",
          "low": "1,648.00",
          "lastPrice": "1,685.00",
          "prevClose": "1,647.05",
          "change": "37.95",
          "percentGain": "2.30"
        },
        {
          "company": "HDFC Bank",
          "high": "1,685.95",
          "low": "1,654.00",
          "lastPrice": "1,685.65",
          "prevClose": "1,651.00",
          "change": "34.65",
          "percentGain": "2.10"
        },
        {
          "company": "HDFC Life",
          "high": "739.50",
          "low": "726.30",
          "lastPrice": "737.80",
          "prevClose": "723.85",
          "change": "13.95",
          "percentGain": "1.93"
        },
        {
          "company": "Shriram Finance",
          "high": "3,430.00",
          "low": "3,353.75",
          "lastPrice": "3,401.90",
          "prevClose": "3,341.20",
          "change": "60.70",
          "percentGain": "1.82"
        }
      ]
    },
    {
      "time": "7:16:53 AM",
      "data": [
        {
          "company": "Wipro",
          "high": "550.00",
          "low": "536.30",
          "lastPrice": "549.60",
          "prevClose": "528.30",
          "change": "21.30",
          "percentGain": "4.03"
        },
        {
          "company": "Tech Mahindra",
          "high": "1,694.35",
          "low": "1,648.00",
          "lastPrice": "1,694.05",
          "prevClose": "1,647.05",
          "change": "47.00",
          "percentGain": "2.85"
        },
        {
          "company": "HDFC Bank",
          "high": "1,686.95",
          "low": "1,654.00",
          "lastPrice": "1,683.40",
          "prevClose": "1,651.00",
          "change": "32.40",
          "percentGain": "1.96"
        },
        {
          "company": "HDFC Life",
          "high": "739.50",
          "low": "726.30",
          "lastPrice": "736.45",
          "prevClose": "723.85",
          "change": "12.60",
          "percentGain": "1.74"
        },
        {
          "company": "Infosys",
          "high": "1,969.50",
          "low": "1,931.10",
          "lastPrice": "1,968.75",
          "prevClose": "1,935.10",
          "change": "33.65",
          "percentGain": "1.74"
        }
      ]
    },
    {
      "time": "7:38:52 AM",
      "data": [
        {
          "company": "Wipro",
          "high": "551.85",
          "low": "536.30",
          "lastPrice": "547.95",
          "prevClose": "528.30",
          "change": "19.65",
          "percentGain": "3.72"
        },
        {
          "company": "Tech Mahindra",
          "high": "1,697.00",
          "low": "1,648.00",
          "lastPrice": "1,690.70",
          "prevClose": "1,647.05",
          "change": "43.65",
          "percentGain": "2.65"
        },
        {
          "company": "Larsen",
          "high": "3,556.90",
          "low": "3,501.30",
          "lastPrice": "3,554.95",
          "prevClose": "3,482.55",
          "change": "72.40",
          "percentGain": "2.08"
        },
        {
          "company": "HDFC Bank",
          "high": "1,686.95",
          "low": "1,654.00",
          "lastPrice": "1,682.65",
          "prevClose": "1,651.00",
          "change": "31.65",
          "percentGain": "1.92"
        },
        {
          "company": "HDFC Life",
          "high": "739.50",
          "low": "726.30",
          "lastPrice": "737.30",
          "prevClose": "723.85",
          "change": "13.45",
          "percentGain": "1.86"
        }
      ]
    },
    {
      "time": "7:50:09 AM",
      "data": [
        {
          "company": "Wipro",
          "high": "551.85",
          "low": "536.30",
          "lastPrice": "549.20",
          "prevClose": "528.30",
          "change": "20.90",
          "percentGain": "3.96"
        },
        {
          "company": "Tech Mahindra",
          "high": "1,697.00",
          "low": "1,648.00",
          "lastPrice": "1,692.00",
          "prevClose": "1,647.05",
          "change": "44.95",
          "percentGain": "2.73"
        },
        {
          "company": "Larsen",
          "high": "3,570.25",
          "low": "3,501.30",
          "lastPrice": "3,568.45",
          "prevClose": "3,482.55",
          "change": "85.90",
          "percentGain": "2.47"
        },
        {
          "company": "HDFC Bank",
          "high": "1,686.95",
          "low": "1,654.00",
          "lastPrice": "1,682.85",
          "prevClose": "1,651.00",
          "change": "31.85",
          "percentGain": "1.93"
        },
        {
          "company": "HDFC Life",
          "high": "739.50",
          "low": "726.30",
          "lastPrice": "736.90",
          "prevClose": "723.85",
          "change": "13.05",
          "percentGain": "1.80"
        }
      ]
    },
    {
      "time": "8:20:45 AM",
      "data": []
    },
    {
      "time": "8:43:29 AM",
      "data": [
        {
          "company": "Wipro",
          "high": "551.85",
          "low": "536.30",
          "lastPrice": "550.20",
          "prevClose": "528.30",
          "change": "21.90",
          "percentGain": "4.15"
        },
        {
          "company": "Tech Mahindra",
          "high": "1,697.00",
          "low": "1,648.00",
          "lastPrice": "1,692.45",
          "prevClose": "1,647.05",
          "change": "45.40",
          "percentGain": "2.76"
        },
        {
          "company": "Larsen",
          "high": "3,573.85",
          "low": "3,501.30",
          "lastPrice": "3,568.10",
          "prevClose": "3,482.55",
          "change": "85.55",
          "percentGain": "2.46"
        },
        {
          "company": "HDFC Bank",
          "high": "1,688.00",
          "low": "1,654.00",
          "lastPrice": "1,687.70",
          "prevClose": "1,651.00",
          "change": "36.70",
          "percentGain": "2.22"
        },
        {
          "company": "ITC",
          "high": "498.80",
          "low": "488.65",
          "lastPrice": "498.00",
          "prevClose": "488.20",
          "change": "9.80",
          "percentGain": "2.01"
        }
      ]
    },
    {
      "time": "8:53:51 AM",
      "data": []
    }
  ],
  "losers": [
    {
      "time": "3:52:49 AM",
      "data": [
        {
          "company": "Axis Bank",
          "high": "1,172.95",
          "low": "1,160.25",
          "lastPrice": "1,160.40",
          "prevClose": "1,172.45",
          "change": "-12.05",
          "percentGain": "-1.03"
        },
        {
          "company": "Bajaj Finance",
          "high": "7,313.85",
          "low": "7,222.55",
          "lastPrice": "7,230.20",
          "prevClose": "7,302.00",
          "change": "-71.80",
          "percentGain": "-0.98"
        },
        {
          "company": "Cipla",
          "high": "1,605.95",
          "low": "1,585.00",
          "lastPrice": "1,587.35",
          "prevClose": "1,595.75",
          "change": "-8.40",
          "percentGain": "-0.53"
        },
        {
          "company": "Titan Company",
          "high": "3,484.55",
          "low": "3,456.00",
          "lastPrice": "3,459.00",
          "prevClose": "3,474.40",
          "change": "-15.40",
          "percentGain": "-0.44"
        },
        {
          "company": "Bharti Airtel",
          "high": "1,695.00",
          "low": "1,679.35",
          "lastPrice": "1,680.20",
          "prevClose": "1,687.40",
          "change": "-7.20",
          "percentGain": "-0.43"
        }
      ]
    },
    {
      "time": "4:18:51 AM",
      "data": []
    },
    {
      "time": "4:41:46 AM",
      "data": []
    },
    {
      "time": "4:51:34 AM",
      "data": [
        {
          "company": "Maruti Suzuki",
          "high": "12,799.00",
          "low": "12,587.20",
          "lastPrice": "12,604.80",
          "prevClose": "12,776.65",
          "change": "-171.85",
          "percentGain": "-1.35"
        },
        {
          "company": "Cipla",
          "high": "1,605.95",
          "low": "1,577.50",
          "lastPrice": "1,580.75",
          "prevClose": "1,595.75",
          "change": "-15.00",
          "percentGain": "-0.94"
        },
        {
          "company": "Bajaj Finance",
          "high": "7,313.85",
          "low": "7,215.45",
          "lastPrice": "7,242.20",
          "prevClose": "7,302.00",
          "change": "-59.80",
          "percentGain": "-0.82"
        },
        {
          "company": "UltraTechCement",
          "high": "11,429.95",
          "low": "11,301.00",
          "lastPrice": "11,335.75",
          "prevClose": "11,421.30",
          "change": "-85.55",
          "percentGain": "-0.75"
        },
        {
          "company": "Bajaj Finserv",
          "high": "1,885.10",
          "low": "1,863.30",
          "lastPrice": "1,865.00",
          "prevClose": "1,876.40",
          "change": "-11.40",
          "percentGain": "-0.61"
        }
      ]
    },
    {
      "time": "5:15:55 AM",
      "data": []
    },
    {
      "time": "5:39:38 AM",
      "data": [
        {
          "company": "Maruti Suzuki",
          "high": "12,799.00",
          "low": "12,555.00",
          "lastPrice": "12,565.30",
          "prevClose": "12,776.65",
          "change": "-211.35",
          "percentGain": "-1.65"
        },
        {
          "company": "UltraTechCement",
          "high": "11,429.95",
          "low": "11,240.00",
          "lastPrice": "11,262.70",
          "prevClose": "11,421.30",
          "change": "-158.60",
          "percentGain": "-1.39"
        },
        {
          "company": "Bajaj Finance",
          "high": "7,313.85",
          "low": "7,205.00",
          "lastPrice": "7,215.35",
          "prevClose": "7,302.00",
          "change": "-86.65",
          "percentGain": "-1.19"
        },
        {
          "company": "Britannia",
          "high": "6,015.00",
          "low": "5,900.00",
          "lastPrice": "5,907.65",
          "prevClose": "5,978.50",
          "change": "-70.85",
          "percentGain": "-1.19"
        },
        {
          "company": "Cipla",
          "high": "1,605.95",
          "low": "1,571.05",
          "lastPrice": "1,578.40",
          "prevClose": "1,595.75",
          "change": "-17.35",
          "percentGain": "-1.09"
        }
      ]
    },
    {
      "time": "5:49:58 AM",
      "data": [
        {
          "company": "Maruti Suzuki",
          "high": "12,799.00",
          "low": "12,555.00",
          "lastPrice": "12,566.00",
          "prevClose": "12,776.65",
          "change": "-210.65",
          "percentGain": "-1.65"
        },
        {
          "company": "UltraTechCement",
          "high": "11,429.95",
          "low": "11,240.00",
          "lastPrice": "11,264.30",
          "prevClose": "11,421.30",
          "change": "-157.00",
          "percentGain": "-1.37"
        },
        {
          "company": "Britannia",
          "high": "6,015.00",
          "low": "5,900.00",
          "lastPrice": "5,911.00",
          "prevClose": "5,978.50",
          "change": "-67.50",
          "percentGain": "-1.13"
        },
        {
          "company": "Bajaj Finance",
          "high": "7,313.85",
          "low": "7,205.00",
          "lastPrice": "7,236.65",
          "prevClose": "7,302.00",
          "change": "-65.35",
          "percentGain": "-0.89"
        },
        {
          "company": "Cipla",
          "high": "1,605.95",
          "low": "1,571.05",
          "lastPrice": "1,581.55",
          "prevClose": "1,595.75",
          "change": "-14.20",
          "percentGain": "-0.89"
        }
      ]
    },
    {
      "time": "6:22:58 AM",
      "data": [
        {
          "company": "Maruti Suzuki",
          "high": "12,799.00",
          "low": "12,541.00",
          "lastPrice": "12,577.35",
          "prevClose": "12,776.65",
          "change": "-199.30",
          "percentGain": "-1.56"
        },
        {
          "company": "UltraTechCement",
          "high": "11,429.95",
          "low": "11,240.00",
          "lastPrice": "11,284.00",
          "prevClose": "11,421.30",
          "change": "-137.30",
          "percentGain": "-1.20"
        },
        {
          "company": "Bajaj Finance",
          "high": "7,313.85",
          "low": "7,205.00",
          "lastPrice": "7,233.45",
          "prevClose": "7,302.00",
          "change": "-68.55",
          "percentGain": "-0.94"
        },
        {
          "company": "Cipla",
          "high": "1,605.95",
          "low": "1,571.05",
          "lastPrice": "1,582.50",
          "prevClose": "1,595.75",
          "change": "-13.25",
          "percentGain": "-0.83"
        },
        {
          "company": "ONGC",
          "high": "292.90",
          "low": "290.00",
          "lastPrice": "290.65",
          "prevClose": "292.55",
          "change": "-1.90",
          "percentGain": "-0.65"
        }
      ]
    },
    {
      "time": "6:45:55 AM",
      "data": [
        {
          "company": "Maruti Suzuki",
          "high": "12,799.00",
          "low": "12,541.00",
          "lastPrice": "12,578.50",
          "prevClose": "12,776.65",
          "change": "-198.15",
          "percentGain": "-1.55"
        },
        {
          "company": "Bajaj Finance",
          "high": "7,313.85",
          "low": "7,205.00",
          "lastPrice": "7,228.75",
          "prevClose": "7,302.00",
          "change": "-73.25",
          "percentGain": "-1.00"
        },
        {
          "company": "ONGC",
          "high": "292.90",
          "low": "289.80",
          "lastPrice": "290.00",
          "prevClose": "292.55",
          "change": "-2.55",
          "percentGain": "-0.87"
        },
        {
          "company": "UltraTechCement",
          "high": "11,429.95",
          "low": "11,240.00",
          "lastPrice": "11,321.95",
          "prevClose": "11,421.30",
          "change": "-99.35",
          "percentGain": "-0.87"
        },
        {
          "company": "Tata Steel",
          "high": "163.38",
          "low": "159.01",
          "lastPrice": "159.28",
          "prevClose": "160.66",
          "change": "-1.38",
          "percentGain": "-0.86"
        }
      ]
    },
    {
      "time": "7:16:53 AM",
      "data": [
        {
          "company": "Maruti Suzuki",
          "high": "12,799.00",
          "low": "12,541.00",
          "lastPrice": "12,583.60",
          "prevClose": "12,776.65",
          "change": "-193.05",
          "percentGain": "-1.51"
        },
        {
          "company": "ONGC",
          "high": "292.90",
          "low": "288.15",
          "lastPrice": "288.30",
          "prevClose": "292.55",
          "change": "-4.25",
          "percentGain": "-1.45"
        },
        {
          "company": "UltraTechCement",
          "high": "11,429.95",
          "low": "11,240.00",
          "lastPrice": "11,270.40",
          "prevClose": "11,421.30",
          "change": "-150.90",
          "percentGain": "-1.32"
        },
        {
          "company": "Cipla",
          "high": "1,605.95",
          "low": "1,571.05",
          "lastPrice": "1,578.65",
          "prevClose": "1,595.75",
          "change": "-17.10",
          "percentGain": "-1.07"
        },
        {
          "company": "Tata Steel",
          "high": "163.38",
          "low": "158.60",
          "lastPrice": "158.94",
          "prevClose": "160.66",
          "change": "-1.72",
          "percentGain": "-1.07"
        }
      ]
    },
    {
      "time": "7:38:52 AM",
      "data": [
        {
          "company": "ONGC",
          "high": "292.90",
          "low": "286.65",
          "lastPrice": "287.15",
          "prevClose": "292.55",
          "change": "-5.40",
          "percentGain": "-1.85"
        },
        {
          "company": "Tata Steel",
          "high": "163.38",
          "low": "158.22",
          "lastPrice": "158.26",
          "prevClose": "160.66",
          "change": "-2.40",
          "percentGain": "-1.49"
        },
        {
          "company": "Tata Steel",
          "high": "163.38",
          "low": "158.22",
          "lastPrice": "158.26",
          "prevClose": "160.66",
          "change": "-2.40",
          "percentGain": "-1.49"
        },
        {
          "company": "Maruti Suzuki",
          "high": "12,799.00",
          "low": "12,541.00",
          "lastPrice": "12,590.00",
          "prevClose": "12,776.65",
          "change": "-186.65",
          "percentGain": "-1.46"
        },
        {
          "company": "UltraTechCement",
          "high": "11,429.95",
          "low": "11,240.00",
          "lastPrice": "11,274.10",
          "prevClose": "11,421.30",
          "change": "-147.20",
          "percentGain": "-1.29"
        }
      ]
    },
    {
      "time": "7:50:09 AM",
      "data": [
        {
          "company": "ONGC",
          "high": "292.90",
          "low": "285.15",
          "lastPrice": "285.85",
          "prevClose": "292.55",
          "change": "-6.70",
          "percentGain": "-2.29"
        },
        {
          "company": "Maruti Suzuki",
          "high": "12,799.00",
          "low": "12,541.00",
          "lastPrice": "12,587.00",
          "prevClose": "12,776.65",
          "change": "-189.65",
          "percentGain": "-1.48"
        },
        {
          "company": "Tata Steel",
          "high": "163.38",
          "low": "158.22",
          "lastPrice": "158.32",
          "prevClose": "160.66",
          "change": "-2.34",
          "percentGain": "-1.46"
        },
        {
          "company": "Tata Steel",
          "high": "163.38",
          "low": "158.22",
          "lastPrice": "158.32",
          "prevClose": "160.66",
          "change": "-2.34",
          "percentGain": "-1.46"
        },
        {
          "company": "UltraTechCement",
          "high": "11,429.95",
          "low": "11,240.00",
          "lastPrice": "11,278.70",
          "prevClose": "11,421.30",
          "change": "-142.60",
          "percentGain": "-1.25"
        }
      ]
    },
    {
      "time": "8:20:45 AM",
      "data": []
    },
    {
      "time": "8:43:29 AM",
      "data": [
        {
          "company": "ONGC",
          "high": "292.90",
          "low": "285.15",
          "lastPrice": "286.85",
          "prevClose": "292.55",
          "change": "-5.70",
          "percentGain": "-1.95"
        },
        {
          "company": "Maruti Suzuki",
          "high": "12,799.00",
          "low": "12,541.00",
          "lastPrice": "12,585.75",
          "prevClose": "12,776.65",
          "change": "-190.90",
          "percentGain": "-1.49"
        },
        {
          "company": "Tata Steel",
          "high": "163.38",
          "low": "158.22",
          "lastPrice": "158.56",
          "prevClose": "160.66",
          "change": "-2.10",
          "percentGain": "-1.31"
        },
        {
          "company": "Tata Steel",
          "high": "163.38",
          "low": "158.22",
          "lastPrice": "158.56",
          "prevClose": "160.66",
          "change": "-2.10",
          "percentGain": "-1.31"
        },
        {
          "company": "UltraTechCement",
          "high": "11,429.95",
          "low": "11,240.00",
          "lastPrice": "11,289.15",
          "prevClose": "11,421.30",
          "change": "-132.15",
          "percentGain": "-1.16"
        }
      ]
    },
    {
      "time": "8:53:51 AM",
      "data": []
    }
  ]
}